django_user_starter/__init__.py
django_user_starter/_version.py
django_user_starter/cli.py
django_user_starter/starter-en.sh
django_user_starter/starter-zh.sh
django_user_starter-0.2.0.dist-info/licenses/LICENSE
django_user_starter-0.2.0.dist-info/METADATA
django_user_starter-0.2.0.dist-info/WHEEL
django_user_starter-0.2.0.dist-info/entry_points.txt
django_user_starter-0.2.0.dist-info/top_level.txt
django_user_starter-0.2.0.dist-info/RECORD
