Metadata-Version: 2.4
Name: django_user_starter
Version: 0.2.0
Summary: A Django starter script with both Chinese and English versions, auto versioning via semantic-release.
Author-email: yaninsanity <admin@jl-blog.com>
License-Expression: MIT
Keywords: django,starter,shell
Classifier: Programming Language :: Python :: 3
Classifier: Framework :: Django
Classifier: Operating System :: OS Independent
Requires-Python: >=3.9
License-File: LICENSE
Requires-Dist: Django>=3.2
Requires-Dist: django-avatar
Requires-Dist: pillow
Requires-Dist: django-jazzmin
Provides-Extra: dev
Requires-Dist: black>=23.0.0; extra == "dev"
Requires-Dist: isort>=5.0.0; extra == "dev"
Requires-Dist: flake8>=6.0.0; extra == "dev"
Requires-Dist: pytest>=7.0.0; extra == "dev"
Requires-Dist: pytest-cov>=4.0.0; extra == "dev"
Requires-Dist: python-semantic-release>=9.0.0; extra == "dev"
Requires-Dist: build>=1.0.0; extra == "dev"
Requires-Dist: twine>=4.0.0; extra == "dev"
Requires-Dist: pre-commit>=3.0.0; extra == "dev"
Dynamic: license-file
